vcf2parquet-0.6.0.dist-info/METADATA
vcf2parquet-0.6.0.dist-info/WHEEL
pyvcf2parquet/__init__.py
pyvcf2parquet/pyvcf2parquet.cpython-39-i386-linux-gnu.so
vcf2parquet-0.6.0.dist-info/RECORD
